[
    {
      "id": 1,
      "heading": "১. অনলাইন বুকিং",
      "description": "কল করে, মেইল করে অথবা ওয়েসবসাইটেই ফর্ম পূরণ করে আপনার বুকিংটি নিন।",
      "imagePath": "./img/worksystem/man-with-desk.webp"
    },
    {
        "id": 2,
        "heading": "2. কনফার্ম করুন",
        "description": "বুকিং নেয়া হয়ে গেলে রাজসেবা আপনার সাথে যোগাযোগ করবে। তখন আপনার অর্ডারটি কনফার্ম করবে।",
        "imagePath": "./img/worksystem/hand-shake.webp"
    },
    {
        "id": 3,
        "heading": "৩. কাজের অবস্থা",
        "description": "অর্ডার কনফার্ম হবার পরে রাজসেবা আপনার কাজ শুরু করবে। আমাদের দক্ষ ও একনিষ্ঠ টেকনিশিয়ান ও কর্মী আপনার কাজ করবে অতি দ্রুত ও সুচারুরুপে।",
        "imagePath": "./img/worksystem/tool.webp"
    },
    {
        "id": 4,
        "heading": "৪. সম্পন্ন",
        "description": "কাজ সম্পন্ন হবার পরে কাজ বুঝে নিয়ে পেমেন্ট সম্পন্ন করে রশিদ নিয়ে নিন। এভাবেই খুব সহজেই হয়ে যান রাজসেবার সেবাগ্রহীতা।",
        "imagePath": "./img/worksystem/tag.webp"
    }
    
  ]
  